utilities/__init__.py
utilities/ai/__init__.py
utilities/ai/openai_chat_client.py
utilities/ai/providers/__init__.py
utilities/ai/providers/azure_openai_provider.py
utilities/ai/providers/base_chat_provider.py
utilities/ai/providers/deepinfra_provider.py
utilities/config/__init__.py
utilities/config/config_parser.py
utilities/config/config_writer.py
utilities/excel/__init__.py
utilities/excel/excel_comparer.py
utilities/gitlab/__init__.py
utilities/gitlab/gitlab_client.py
utilities/jira/__init__.py
utilities/jira/jira_client.py
utilities/logger/__init__.py
utilities/logger/log_decorator.py
utilities/logger/log_wrapper.py
utilities/logger/logger.py
utilities/os/__init__.py
utilities/os/content_scanner.py
utilities/os/directory_event.py
utilities/os/directory_watcher_crossplatform.py
utilities/os/directory_watcher_windows.py
utilities/os/file_scanner.py
utilities/teams/__init__.py
utilities/teams/teams_client.py
utilities/utility_base.py
py3_utilities-1.2.0.dist-info/licenses/LICENSE
py3_utilities-1.2.0.dist-info/METADATA
py3_utilities-1.2.0.dist-info/WHEEL
py3_utilities-1.2.0.dist-info/RECORD
