Metadata-Version: 2.4
Name: py3-utilities
Version: 1.2.0
Summary: Private utility package
License-File: LICENSE
Author: Gabor Erdelyi
Author-email: e.gabor94@gmail.com
Requires-Python: >=3.11,<4.0
Classifier: Programming Language :: Python :: 3
Classifier: Programming Language :: Python :: 3.11
Classifier: Programming Language :: Python :: 3.12
Classifier: Programming Language :: Python :: 3.13
Classifier: Programming Language :: Python :: 3.14
Provides-Extra: ai
Provides-Extra: all
Provides-Extra: config
Provides-Extra: excel
Provides-Extra: gitlab
Provides-Extra: jira
Provides-Extra: logger
Provides-Extra: os-crossplatform
Provides-Extra: os-windows
Provides-Extra: teams
Requires-Dist: aiofiles (>=24.1.0,<24.2.0) ; extra == "all"
Requires-Dist: aiofiles (>=24.1.0,<24.2.0) ; extra == "os-crossplatform"
Requires-Dist: aiofiles (>=24.1.0,<24.2.0) ; extra == "os-windows"
Requires-Dist: aiohttp (>=3.12.11,<3.13.0) ; extra == "ai"
Requires-Dist: aiohttp (>=3.12.11,<3.13.0) ; extra == "all"
Requires-Dist: aiohttp (>=3.12.11,<3.13.0) ; extra == "jira"
Requires-Dist: azure-ai-documentintelligence (>=1.0.2,<1.1.0) ; extra == "ai"
Requires-Dist: azure-ai-documentintelligence (>=1.0.2,<1.1.0) ; extra == "all"
Requires-Dist: azure-core (>=1.33.0,<1.34.0) ; extra == "ai"
Requires-Dist: azure-core (>=1.33.0,<1.34.0) ; extra == "all"
Requires-Dist: colorlog (>=6.9.0,<6.10.0) ; extra == "all"
Requires-Dist: colorlog (>=6.9.0,<6.10.0) ; extra == "logger"
Requires-Dist: gitpython (>=3.1.44,<3.2.0) ; extra == "all"
Requires-Dist: gitpython (>=3.1.44,<3.2.0) ; extra == "gitlab"
Requires-Dist: numpy (>=2.3.0,<2.4.0) ; extra == "all"
Requires-Dist: numpy (>=2.3.0,<2.4.0) ; extra == "excel"
Requires-Dist: openai (>=1.84.0,<1.85.0) ; extra == "ai"
Requires-Dist: openai (>=1.84.0,<1.85.0) ; extra == "all"
Requires-Dist: openpyxl (>=3.1.5,<3.2.0) ; extra == "all"
Requires-Dist: openpyxl (>=3.1.5,<3.2.0) ; extra == "excel"
Requires-Dist: openpyxl (>=3.1.5,<3.2.0) ; extra == "os-crossplatform"
Requires-Dist: openpyxl (>=3.1.5,<3.2.0) ; extra == "os-windows"
Requires-Dist: pandas (>=2.3.0,<2.4.0) ; extra == "all"
Requires-Dist: pandas (>=2.3.0,<2.4.0) ; extra == "excel"
Requires-Dist: pandas (>=2.3.0,<2.4.0) ; extra == "os-crossplatform"
Requires-Dist: pandas (>=2.3.0,<2.4.0) ; extra == "os-windows"
Requires-Dist: pdfplumber (>=0.11.6,<0.12.0) ; extra == "all"
Requires-Dist: pdfplumber (>=0.11.6,<0.12.0) ; extra == "os-crossplatform"
Requires-Dist: pdfplumber (>=0.11.6,<0.12.0) ; extra == "os-windows"
Requires-Dist: pip-system-certs (>=4.0,<4.1) ; extra == "all"
Requires-Dist: pip-system-certs (>=4.0,<4.1) ; extra == "jira"
Requires-Dist: python-docx (>=1.1.2,<1.2.0) ; extra == "all"
Requires-Dist: python-docx (>=1.1.2,<1.2.0) ; extra == "os-crossplatform"
Requires-Dist: python-docx (>=1.1.2,<1.2.0) ; extra == "os-windows"
Requires-Dist: python-dotenv (>=1.1.0,<1.2.0) ; extra == "all"
Requires-Dist: python-dotenv (>=1.1.0,<1.2.0) ; extra == "config"
Requires-Dist: python-gitlab (>=6.0.0,<6.1.0) ; extra == "all"
Requires-Dist: python-gitlab (>=6.0.0,<6.1.0) ; extra == "gitlab"
Requires-Dist: python-json-logger (>=3.3.0,<3.4.0) ; extra == "all"
Requires-Dist: python-json-logger (>=3.3.0,<3.4.0) ; extra == "logger"
Requires-Dist: pywin32 (>=310,<311) ; extra == "all"
Requires-Dist: pywin32 (>=310,<311) ; extra == "os-windows"
Requires-Dist: pyyaml (>=6.0.2,<6.1.0) ; extra == "all"
Requires-Dist: pyyaml (>=6.0.2,<6.1.0) ; extra == "config"
Requires-Dist: requests (>=2.32.4,<2.33.0) ; extra == "all"
Requires-Dist: requests (>=2.32.4,<2.33.0) ; extra == "teams"
Requires-Dist: tomli-w (>=1.2.0,<1.3.0) ; extra == "all"
Requires-Dist: tomli-w (>=1.2.0,<1.3.0) ; extra == "config"
Requires-Dist: watchdog (>=6.0.0,<6.1.0) ; extra == "all"
Requires-Dist: watchdog (>=6.0.0,<6.1.0) ; extra == "os-crossplatform"
